otools_rpc/__init__.py
otools_rpc/db_manager/__init__.py
otools_rpc/db_manager/database_utils.py
otools_rpc/external_api/__init__.py
otools_rpc/external_api/cache.py
otools_rpc/external_api/common.py
otools_rpc/external_api/environment.py
otools_rpc/external_api/recordset.py
otools_rpc/external_api/utils.py
otools_rpc-0.5.2.dist-info/LICENSE.txt
otools_rpc-0.5.2.dist-info/METADATA
otools_rpc-0.5.2.dist-info/WHEEL
otools_rpc-0.5.2.dist-info/top_level.txt
otools_rpc-0.5.2.dist-info/RECORD
