Metadata-Version: 2.1
Name: otools-rpc
Version: 0.5.2
Summary: A tool to interact with Odoo's external API.
Home-page: https://github.com/MrFaBemol/otools-rpc
Author: Gautier Casabona
Author-email: gcasabona.pro@gmail.com
License: MIT
Platform: UNKNOWN
Classifier: Development Status :: 3 - Alpha
Classifier: License :: OSI Approved :: MIT License
Classifier: Programming Language :: Python :: 3.8
Classifier: Operating System :: OS Independent
Classifier: Intended Audience :: Developers
Classifier: Natural Language :: English
Requires-Python: >=3.8
License-File: LICENSE.txt
Requires-Dist: loguru (>=0.7.0)
Requires-Dist: requests
Provides-Extra: dev
Requires-Dist: pytest (>=7.0) ; extra == 'dev'
Requires-Dist: twine (>=4.0.2) ; extra == 'dev'
